steam_vdf/__init__.py
steam_vdf/cli.py
steam_vdf/storage.py
steam_vdf/users.py
steam_vdf/utils.py
steam_vdf-0.1.10.dist-info/LICENSE
steam_vdf-0.1.10.dist-info/METADATA
steam_vdf-0.1.10.dist-info/WHEEL
steam_vdf-0.1.10.dist-info/entry_points.txt
steam_vdf-0.1.10.dist-info/RECORD
