Metadata-Version: 2.3
Name: steam-vdf
Version: 0.1.10
Summary: Steam VDF file parser
Author: Your Name
Author-email: your.email@example.com
Requires-Python: >=3.10,<4.0
Classifier: Programming Language :: Python :: 3
Classifier: Programming Language :: Python :: 3.10
Classifier: Programming Language :: Python :: 3.11
Classifier: Programming Language :: Python :: 3.12
Classifier: Programming Language :: Python :: 3.13
Requires-Dist: humanize (>=4.9.0,<5.0.0)
Requires-Dist: psutil
Requires-Dist: vdf (>=3.4,<4.0)
